qqmusic_api/__init__.py
qqmusic_api/album.py
qqmusic_api/comment.py
qqmusic_api/login.py
qqmusic_api/lyric.py
qqmusic_api/mv.py
qqmusic_api/recommend.py
qqmusic_api/search.py
qqmusic_api/singer.py
qqmusic_api/song.py
qqmusic_api/songlist.py
qqmusic_api/top.py
qqmusic_api/user.py
qqmusic_api/exceptions/__init__.py
qqmusic_api/exceptions/api_exception.py
qqmusic_api/utils/__init__.py
qqmusic_api/utils/common.py
qqmusic_api/utils/credential.py
qqmusic_api/utils/device.py
qqmusic_api/utils/mqtt.py
qqmusic_api/utils/network.py
qqmusic_api/utils/qimei.py
qqmusic_api/utils/session.py
qqmusic_api/utils/sign.py
qqmusic_api/utils/tripledes.py
qqmusic_api_python-0.4.1.dist-info/METADATA
qqmusic_api_python-0.4.1.dist-info/WHEEL
qqmusic_api_python-0.4.1.dist-info/licenses/LICENSE
qqmusic_api_python-0.4.1.dist-info/RECORD
