Metadata-Version: 2.4
Name: qqmusic-api-python
Version: 0.4.1
Summary: QQ音乐API封装库
Project-URL: homepage, https://luren-dc.github.io/QQMusicApi/
Project-URL: repository, https://github.com/luren-dc/QQMusicApi
Project-URL: documentation, https://luren-dc.github.io/QQMusicApi/
Author-email: Luren <68656403+luren-dc@users.noreply.github.com>
Maintainer-email: Luren <68656403+luren-dc@users.noreply.github.com>
License: MIT
License-File: LICENSE
Keywords: api,music,qqmusic,tencentmusic
Classifier: Development Status :: 4 - Beta
Classifier: Framework :: Pytest
Classifier: Framework :: aiohttp
Classifier: License :: OSI Approved :: MIT License
Classifier: Natural Language :: Chinese (Simplified)
Classifier: Programming Language :: Python
Classifier: Programming Language :: Python :: 3 :: Only
Classifier: Programming Language :: Python :: 3.10
Classifier: Programming Language :: Python :: Implementation :: CPython
Classifier: Topic :: Software Development :: Libraries :: Python Modules
Requires-Python: >=3.10
Requires-Dist: cryptography>=46.0.3
Requires-Dist: httpx-ws>=0.8.2
Requires-Dist: httpx[http2]>=0.27.0
Requires-Dist: orjson>=3.10.15
Requires-Dist: typing-extensions>=4.12.2
